xcm_parser/__init__.py
xcm_parser/__main__.py
xcm_parser/class_model.peg
xcm_parser/class_model_parser.py
xcm_parser/class_model_visitor.py
xcm_parser/exceptions.py
xcm_parser/log.conf
xcm_parser-0.3.5.dist-info/LICENSE
xcm_parser-0.3.5.dist-info/METADATA
xcm_parser-0.3.5.dist-info/WHEEL
xcm_parser-0.3.5.dist-info/entry_points.txt
xcm_parser-0.3.5.dist-info/top_level.txt
xcm_parser-0.3.5.dist-info/RECORD
