Metadata-Version: 2.2
Name: xcm-parser
Version: 0.3.5
Summary: Executable Shlaer-Mellor Class Model Parser
Author-email: Leon Starr <leon_starr@modelint.com>
License: MIT License
Project-URL: repository, https://github.com/modelint/xcm-parser
Project-URL: documentation, https://github.com/modelint/xcm-parser/wiki
Keywords: action language,executable uml,class model,mbse,xuml,xtuml,platform independent,sysml
Classifier: License :: OSI Approved :: MIT License
Classifier: Programming Language :: Python
Classifier: Programming Language :: Python :: 3
Requires-Python: >=3.11
License-File: LICENSE
Requires-Dist: Arpeggio
Requires-Dist: tomli; python_version < "3.11"
Provides-Extra: build
Requires-Dist: build; extra == "build"
Requires-Dist: twine; extra == "build"
Provides-Extra: dev
Requires-Dist: bump2version; extra == "dev"
Requires-Dist: pytest; extra == "dev"
